{"endpoint_map":{},"endpoint_regional":"regional","standard":{"cn-qingdao":"alikafka.cn-qingdao.aliyuncs.com","cn-beijing":"alikafka.cn-beijing.aliyuncs.com","cn-zhangjiakou":"alikafka.cn-zhangjiakou.aliyuncs.com","cn-huhehaote":"alikafka.cn-huhehaote.aliyuncs.com","cn-wulanchabu":"alikafka.cn-wulanchabu.aliyuncs.com","cn-hangzhou":"alikafka.cn-hangzhou.aliyuncs.com","cn-shanghai":"alikafka.cn-shanghai.aliyuncs.com","cn-shenzhen":"alikafka.cn-shenzhen.aliyuncs.com","cn-heyuan":"alikafka.cn-heyuan.aliyuncs.com","cn-guangzhou":"alikafka.cn-guangzhou.aliyuncs.com","cn-chengdu":"alikafka.cn-chengdu.aliyuncs.com","cn-hongkong":"alikafka.cn-hongkong.aliyuncs.com","ap-northeast-1":"alikafka.ap-northeast-1.aliyuncs.com","ap-southeast-1":"alikafka.ap-southeast-1.aliyuncs.com","ap-southeast-2":"alikafka.ap-southeast-2.aliyuncs.com","ap-southeast-3":"alikafka.ap-southeast-3.aliyuncs.com","ap-southeast-5":"alikafka.ap-southeast-5.aliyuncs.com","us-east-1":"alikafka.us-east-1.aliyuncs.com","us-west-1":"alikafka.us-west-1.aliyuncs.com","eu-west-1":"alikafka.eu-west-1.aliyuncs.com","eu-central-1":"alikafka.eu-central-1.aliyuncs.com","ap-south-1":"alikafka.ap-south-1.aliyuncs.com","cn-hangzhou-finance":"alikafka.cn-hangzhou-finance.aliyuncs.com","cn-shanghai-finance-1":"alikafka.cn-shanghai-finance-1.aliyuncs.com","cn-shenzhen-finance-1":"alikafka.cn-shenzhen-finance-1.aliyuncs.com","cn-north-2-gov-1":"alikafka.cn-north-2-gov-1.aliyuncs.com","cn-beijing-finance-1":"alikafka.cn-beijing-finance-1.aliyuncs.com","cn-huhehaote-nebula-1":"alikafka.cn-huhehaote-nebula-1.aliyuncs.com","cn-qingdao-nebula":"alikafka.cn-qingdao-nebula.aliyuncs.com"},"regions":["cn-qingdao","cn-beijing","cn-zhangjiakou","cn-huhehaote","cn-wulanchabu","cn-hangzhou","cn-shanghai","cn-shenzhen","cn-heyuan","cn-guangzhou","cn-chengdu","cn-hongkong","ap-northeast-1","ap-southeast-1","ap-southeast-2","ap-southeast-3","ap-southeast-5","us-east-1","us-west-1","eu-west-1","eu-central-1","ap-south-1","cn-hangzhou-finance","cn-shanghai-finance-1","cn-shenzhen-finance-1","cn-north-2-gov-1","cn-beijing-finance-1","cn-huhehaote-nebula-1","cn-qingdao-nebula"],"endpoint_health":[]}
