<?xml version='1.0' encoding='UTF-8'?><Api responseBodyIsOriginalObject="" authType="AK" responseLog="disable" isolationType="outer" parameterType="Single" product="Rds" visibility="Private" akProvenStatus="Disable" version="2014-08-15" keepClientResourceOwnerId="false" name="PreCheckCreateOrderForClone" showJsonItemName="true" status="online"><IsvProtocol protocol="HTTPS|HTTP" method="POST|GET" /><ErrorMapping exceptionExpress="success=false,code,message,httpStatusCode"><ErrorCodes /></ErrorMapping><IspProtocol interface="com.aliyun.abs.rds.service.v20140815.PreCheckDriverOrderService" timeout="10000" protocol="dubbo" invokeType="com.aliyun.abs.rds.service.domain.v20140815.CreateOrderRequest" method="createOrder" version="2014-08-15" retries="-1" /><Parameters><Parameter name="mfaPresent" tagName="ak_mfa_present" type="Boolean" required="false" tagPosition="System" checkBlank="false"/><Parameter name="sslCallerIp" tagName="app_ip" type="String" required="false" tagPosition="System" checkBlank="false"/><Parameter name="sslCallerSecurityTransport" tagName="security_transport" type="Boolean" required="false" tagPosition="System" checkBlank="false"/><Parameter name="sslProxyTrustTransportInfo" tagName="proxy_trust_transport_info" type="Boolean" required="false" tagPosition="System" checkBlank="false"/><Parameter name="sslProxyCallerSecurityTransport" tagName="proxy_original_security_transport" type="Boolean" required="false" tagPosition="System" checkBlank="false"/><Parameter name="sslProxyCallerIp" tagName="proxy_original_source_ip" type="String" required="false" tagPosition="System" checkBlank="false"/><Parameter name="requestId" tagName="RequestId" type="String" required="false" tagPosition="System" checkBlank="false"/><Parameter name="callerType" tagName="callerType" type="String" required="false" tagPosition="System" checkBlank="false"/><Parameter name="stsSecurityToken" tagName="SecurityToken" type="String" required="false" tagPosition="System" checkBlank="false"/><Parameter name="appKey" tagName="AccessKeyId" type="String" required="false" tagPosition="Query" checkBlank="false" visibility="Public"/><Parameter name="stsAccessKeyId" tagName="AccessKeyId" type="String" required="false" tagPosition="Query" checkBlank="false" visibility="Public"/><Parameter name="apiName" tagName="Action" type="String" required="false" tagPosition="Query" checkBlank="false" visibility="Public"/><Parameter name="callerBid" tagName="callerBid" type="String" required="false" tagPosition="System" checkBlank="false"/><Parameter name="callerUid" tagName="callerUid" type="Long" required="false" tagPosition="System" checkBlank="false"/><Parameter name="ownerId" tagName="OwnerId" type="Long" required="false" tagPosition="Query" checkBlank="false" visibility="Public"/><Parameter name="callerUidLoginEmail" tagName="callerUidEmail" type="String" required="false" tagPosition="System" checkBlank="false"/><Parameter name="callerBidLoginEmail" tagName="callerBidEmail" type="String" required="false" tagPosition="System" checkBlank="false"/><Parameter name="ownerIdLoginEmail" tagName="ownerIdLoginEmail" type="String" required="false" tagPosition="System" checkBlank="false"/><Parameter name="resourceOwnerAccount" tagName="ResourceOwnerAccount" type="String" required="false" tagPosition="Query" checkBlank="false" visibility="Public"/><Parameter name="resourceOwnerId" tagName="ResourceOwnerId" type="Long" required="false" tagPosition="Query" checkBlank="false" visibility="Public"/><Parameter name="enable" tagName="enable" type="Boolean" required="false" tagPosition="System" checkBlank="false"/><Parameter name="requestContent" tagName="requestContent" type="String" required="false" tagPosition="System" checkBlank="false"/><Parameter name="token" tagName="ClientToken" type="String" required="false" tagPosition="Query" checkBlank="false" visibility="Public"/><Parameter name="commodity" tagName="CommodityCode" type="String" required="true" tagPosition="Query" docRequired="true" checkBlank="false" visibility="Public"/><Parameter name="dbInstanceId" tagName="DBInstanceId" type="String" required="false" tagPosition="Query" checkBlank="false" visibility="Public"/><Parameter name="dbInstanceClass" tagName="DBInstanceClass" type="String" required="true" tagPosition="Query" docRequired="true" checkBlank="false" visibility="Public"/><Parameter name="dbInstanceStorage" tagName="DBInstanceStorage" type="Integer" required="true" tagPosition="Query" docRequired="true" checkBlank="false" visibility="Public"/><Parameter name="dbInstanceStorageType" tagName="DBInstanceStorageType" type="String" required="false" tagPosition="Query" checkBlank="false" visibility="Public"/><Parameter name="payType" tagName="PayType" type="String" required="false" tagPosition="Query" checkBlank="false" visibility="Public"><Switch><Cases><Case value="POSTPAY" tagValue="Postpaid"/><Case value="PREPAY" tagValue="Prepaid"/></Cases></Switch></Parameter><Parameter name="instanceNetworkType" tagName="InstanceNetworkType" type="String" required="false" tagPosition="Query" checkBlank="false" visibility="Public"><Switch><Cases><Case value="VPC" tagValue="VPC"/><Case value="Classic" tagValue="Classic"/></Cases></Switch></Parameter><Parameter name="usedTime" tagName="UsedTime" type="String" required="false" tagPosition="Query" checkBlank="false" visibility="Public"/><Parameter name="timeType" tagName="TimeType" type="String" required="false" tagPosition="Query" checkBlank="false" visibility="Public"><Switch><Cases><Case value="1" tagValue="Year"/><Case value="2" tagValue="Month"/><Case value="3" tagValue="Day"/><Case value="4" tagValue="Hour"/></Cases></Switch></Parameter><Parameter name="quantity" tagName="Quantity" type="Integer" required="true" tagPosition="Query" docRequired="true" checkBlank="false" visibility="Public"/><Parameter name="autoPay" tagName="AutoPay" type="Boolean" required="false" tagPosition="Query" checkBlank="false" visibility="Public"/><Parameter name="dbInstanceUsedType" tagName="InstanceUsedType" type="Integer" required="false" tagPosition="Query" checkBlank="false" defaultValue="0" visibility="Public"><Switch><Cases><Case value="0" tagValue="0"/><Case value="1" tagValue="3"/></Cases></Switch></Parameter><Parameter name="resource" tagName="Resource" type="String" required="false" tagPosition="Query" checkBlank="false" defaultValue="buy" visibility="Public"/><Parameter name="vpcId" tagName="VPCId" type="String" required="false" tagPosition="Query" checkBlank="false" visibility="Public"/><Parameter name="vswitchId" tagName="VSwitchId" type="String" required="false" tagPosition="Query" checkBlank="false" visibility="Public"/><Parameter name="cloudInstanceIp" tagName="PrivateIpAddress" type="String" required="false" tagPosition="Query" checkBlank="false" visibility="Public"/><Parameter name="countryCode" tagName="CountryCode" type="String" required="false" tagPosition="Query" checkBlank="false" visibility="Public"/><Parameter name="currencyCode" tagName="CurrencyCode" type="String" required="false" tagPosition="Query" checkBlank="false" visibility="Public"/><Parameter name="autoRenew" tagName="AutoRenew" type="String" required="false" tagPosition="Query" checkBlank="false" visibility="Public"/><Parameter name="agentId" tagName="AgentId" type="String" required="false" tagPosition="Query" checkBlank="false" visibility="Public"/><Parameter name="zoneId" tagName="ZoneId" type="String" required="false" tagPosition="Query" checkBlank="false" visibility="Public"/><Parameter name="promotionCode" tagName="PromotionCode" type="String" required="false" tagPosition="Query" checkBlank="false" visibility="Public"/><Parameter name="businessInfo" tagName="BusinessInfo" type="String" required="false" tagPosition="Query" checkBlank="false" visibility="Public"/><Parameter name="cloneInstance" tagName="CloneInstanceDefaultValue" type="String" required="false" tagPosition="Query" checkBlank="false" defaultValue="true" visibility="Public"/><Parameter name="dbInstanceDescription" tagName="DBInstanceDescription" type="String" required="false" tagPosition="Query" checkBlank="false" visibility="Public"/><Parameter name="dbNames" tagName="DBNames" type="String" required="false" tagPosition="Query" checkBlank="false" visibility="Public"/><Parameter name="backupSetId" tagName="BackupId" type="String" required="false" tagPosition="Query" checkBlank="false" visibility="Public"/><Parameter name="restoreTime" tagName="RestoreTime" type="String" required="false" tagPosition="Query" checkBlank="false" visibility="Public"/><Parameter name="ownerAccount" tagName="OwnerAccount" type="String" required="false" tagPosition="Query" checkBlank="false" visibility="Public"/><Parameter name="resourceGroupId" tagName="ResourceGroupId" type="String" required="false" tagPosition="Query" checkBlank="false" visibility="Public"/><Parameter name="tableMeta" tagName="TableMeta" type="String" required="false" tagPosition="Query" checkBlank="false" visibility="Public"/><Parameter name="restoreTable" tagName="RestoreTable" type="String" required="false" tagPosition="Query" checkBlank="false" visibility="Public"/><Parameter name="nodeType" tagName="NodeType" type="String" required="false" tagPosition="Query" checkBlank="false" visibility="Public"/><Parameter name="regionId" tagName="RegionId" type="String" required="false" tagPosition="Query" checkBlank="false" visibility="Public"/></Parameters><FlowControl controlUnit="Minute" userDefault="100" apiDefault="20000" /><ResultMapping><Member tagName="RequestId" visibility="Public" type="String" name="requestId"/><Member tagName="PreCheckResult" visibility="Public" type="Boolean" name="data.preCheckResult"/><Array tagName="Failures" visibility="Public" itemName="Failures" name="data.failures" nullToEmpty="false"><Member tagName="Code" visibility="Public" type="String" name="code"/><Member tagName="Message" visibility="Public" type="String" name="message"/></Array></ResultMapping></Api>
