<?xml version='1.0' encoding='UTF-8'?><Api responseBodyIsOriginalObject="" authType="AK" responseLog="enable" isolationType="outer" parameterType="Single" product="ARMS" visibility="Public" akProvenStatus="Disable" version="2019-08-08" keepClientResourceOwnerId="false" name="QueryMetricByPage" showJsonItemName="false" status="online"><IsvProtocol protocol="HTTPS|HTTP" method="POST|GET" /><ErrorMapping exceptionExpress="success=false,code,message,httpStatusCode,dynamicCode,dynamicMessage"><ErrorCodes /></ErrorMapping><IspProtocol sign="true" signKeyName="arms-hz-central" timeout="60000" protocol="http" httpHost="http://arms.${regionId}.aliyun-inc.com:8099/metric/AppMetricQueryByPage.json" resultType="Object" signPolicy="Local" httpsValidation="true" retries="-1" /><Parameters><Parameter name="requestId" tagName="RequestId" type="String" required="false" tagPosition="System" checkBlank="false"/><Parameter name="userId" tagName="callerUid" type="Long" required="false" tagPosition="System" checkBlank="false"/><Parameter name="parentId" tagName="callerParentId" type="Long" required="false" tagPosition="System" checkBlank="false"/><Parameter name="callerType" tagName="callerType" type="String" required="false" tagPosition="System" checkBlank="false"/><Parameter name="intervalInSec" tagName="IntervalInSec" type="Integer" required="false" tagPosition="Query" docRequired="true" checkBlank="false" defaultValue="2147483647" minValue="0" maxValue="2147483647" visibility="Public"/><Parameter name="startTime" tagName="StartTime" type="Long" required="true" tagPosition="Query" docRequired="true" checkBlank="false" minValue="0" maxValue="9223372036854775806" visibility="Public"/><Parameter name="endTime" tagName="EndTime" type="Long" required="true" tagPosition="Query" docRequired="true" checkBlank="false" minValue="0" maxValue="9223372036854775806" visibility="Public"/><Parameter name="accessKeyId" tagName="AccessKeyId" type="String" required="false" tagPosition="System" checkBlank="false"/><Parameter name="securityToken" tagName="SecurityToken" type="String" required="false" tagPosition="System" checkBlank="false"/><Parameter name="orderBy" tagName="OrderBy" type="String" required="false" tagPosition="Query" checkBlank="false" visibility="Public"/><Parameter name="filters" tagName="Filters" type="RepeatList" required="false" tagPosition="Query" checkRepeatListAll="false" maxNumber="5" invokeDataType="Map" visibility="Public"><Parameters><Parameter name="key" tagName="Key" type="String" required="false" checkRepeatListAll="false" checkBlank="false" visibility="Public"/><Parameter name="value" tagName="Value" type="String" required="false" checkRepeatListAll="false" checkBlank="false" visibility="Public"/></Parameters></Parameter><Parameter name="dimensions" tagName="Dimensions" type="RepeatList" required="false" tagPosition="Query" checkRepeatListAll="false" maxNumber="5" subType="String" invokeDataType="Map" visibility="Public"/><Parameter name="metric" tagName="Metric" type="String" required="true" tagPosition="Query" docRequired="true" checkBlank="false" visibility="Public"/><Parameter name="measures" tagName="Measures" type="RepeatList" required="true" tagPosition="Query" checkRepeatListAll="false" maxNumber="5" subType="String" invokeDataType="Map" visibility="Public"/><Parameter name="order" tagName="Order" type="String" required="false" tagPosition="Query" checkBlank="false" visibility="Public"/><Parameter name="regionId" tagName="RegionId" type="String" required="false" tagPosition="Host" checkBlank="false"/><Parameter name="proxyUserId" tagName="ProxyUserId" type="String" required="false" tagPosition="Query" docRequired="false" checkBlank="false" visibility="Private"/><Parameter name="consistencyDataKey" tagName="ConsistencyDataKey" type="String" required="false" tagPosition="Query" docRequired="false" checkBlank="false" visibility="Private"/><Parameter name="consistencyQueryStrategy" tagName="ConsistencyQueryStrategy" type="String" required="false" tagPosition="Query" docRequired="false" checkBlank="false" visibility="Private"/><Parameter name="currentPage" tagName="CurrentPage" type="Integer" required="false" tagPosition="Query" checkBlank="false" defaultValue="1" minValue="1" maxValue="2147483647" visibility="Public"/><Parameter name="pageSize" tagName="PageSize" type="Integer" required="false" tagPosition="Query" checkBlank="false" defaultValue="10" minValue="1" maxValue="2147483647" visibility="Public"/><Parameter name="customFilters" tagName="CustomFilters" type="RepeatList" required="false" tagPosition="Query" checkRepeatListAll="false" maxNumber="5" subType="String" invokeDataType="Json" visibility="Public"/></Parameters><FlowControl controlUnit="Second" apiDefault="1000" /><PreIspProtocol timeout="60000" protocol="http" httpHost="http://arms.${regionId}.aliyun-inc.com:8099/metric/AppMetricQueryByPage.json" resultType="Object" httpsValidation="true" retries="-1" /><ResultMapping><Member tagName="RequestId" visibility="Public" type="String" name="requestId" nullToEmpty="true"/><Member tagName="Code" visibility="Public" type="String" name="code" nullToEmpty="false"/><Member tagName="Success" visibility="Public" type="Boolean" name="success" nullToEmpty="false"/><Member tagName="Message" visibility="Public" type="String" name="message" nullToEmpty="false"/><Struct tagName="Data" visibility="Public" name="data" nullToEmpty="true"><Member tagName="Total" visibility="Public" type="Integer" name="total" nullToEmpty="true"/><Member tagName="Page" visibility="Public" type="Integer" name="page" nullToEmpty="true"/><Member tagName="PageSize" visibility="Public" type="Integer" name="pageSize" nullToEmpty="true"/><List tagName="Items" visibility="Public" itemName="Items" name="items" nullToEmpty="true" type="Map"/></Struct></ResultMapping></Api>
