<?xml version='1.0' encoding='UTF-8'?><Api responseBodyIsOriginalObject="" authType="AK,PrivateKey" isolationType="outer" parameterType="Single" product="Ft" visibility="Public" akProvenStatus="Disable" version="2015-02-02" name="RoaDubboApi" showJsonItemName="true" status="online"><IsvProtocol pattern="/RoaDubboApi" protocol="HTTP|HTTPS" method="GET" /><ErrorMapping><ErrorCodes /></ErrorMapping><IspProtocol interface="com.aliyun.pop.api.service.FtTestService" timeout="10000" protocol="dubbo" invokeType="com.aliyun.pop.api.param.FtTestParam" method="getData" version="1.0.0" retries="-1" /><Parameters><Parameter name="success" tagName="x-acs-success" type="Boolean" required="false" tagPosition="Header" checkBlank="false"/><Parameter name="stringValue" tagName="x-acs-string-value" type="String" required="false" tagPosition="Header" checkBlank="false"/><Parameter name="regionId" tagName="RegionId" type="String" required="false" tagPosition="System" checkBlank="false"/><Parameter name="callerUid" tagName="callerUid" type="Long" required="false" tagPosition="System" checkBlank="false"/><Parameter name="callerBid" tagName="callerBid" type="String" required="false" tagPosition="System" checkBlank="false"/><Parameter name="proxy_trust_transport_info" tagName="proxy_trust_transport_info" type="Boolean" required="false" tagPosition="System" checkBlank="false"/><Parameter name="ak_mfa_present" tagName="ak_mfa_present" type="Boolean" required="false" tagPosition="System" checkBlank="false"/><Parameter name="callerType" tagName="callerType" type="String" required="false" tagPosition="System" checkBlank="false"/><Parameter name="callerParentId" tagName="callerParentId" type="Long" required="false" tagPosition="System" checkBlank="false"/><Parameter name="resourceOwnerId" tagName="ResourceOwnerId" type="Long" required="false" tagPosition="System" checkBlank="false"/><Parameter name="app_ip" tagName="app_ip" type="String" required="false" tagPosition="System" checkBlank="false"/><Parameter name="proxy_original_source_ip" tagName="proxy_original_source_ip" type="String" required="false" tagPosition="Query" checkBlank="false"/><Parameter name="proxy_original_security_transport" tagName="proxy_original_security_transport" type="Boolean" required="false" tagPosition="Query" checkBlank="false"/><Parameter name="security_transport" tagName="security_transport" type="Boolean" required="false" tagPosition="System" checkBlank="false"/><Parameter name="requestId" tagName="RequestId" type="String" required="false" tagPosition="System" checkBlank="false"/></Parameters><ResultMapping><Member tagName="RegionId" type="String" name="regionId"/><Member tagName="Success" type="String" name="success"/><Member tagName="callerUid" type="String" name="callerUid"/><Member tagName="callerBid" type="String" name="callerBid"/><Member tagName="proxy_trust_transport_info" type="String" name="proxy_trust_transport_info"/><Member tagName="ak_mfa_present" type="String" name="ak_mfa_present"/><Member tagName="callerType" type="String" name="callerType"/><Member tagName="callerParentId" type="String" name="callerParentId"/><Member tagName="resourceOwnerId" type="String" name="resourceOwnerId"/><Member tagName="app_ip" type="String" name="app_ip"/><Member tagName="proxy_original_source_ip" type="String" name="proxy_original_source_ip"/><Member tagName="proxy_original_security_transport" type="String" name="proxy_original_security_transport"/><Member tagName="security_transport" type="String" name="security_transport"/><Member tagName="requestId" type="String" name="requestId"/></ResultMapping></Api>
